{
  "output": {
    "machine_info": {
      "date": "Sun Sep 21 09:40:03 2025",
      "nnodes": 8,
      "nproc_per_node": 4,
      "nproc_total": 32,
      "cpu": {
        "name": "AMD EPYC 7763 64-Core Processor                ",
        "cpu_memory_per_node_gib": 251,
        "total_cpu_memory_gib": 2008
      },
      "ngpus_per_node": 4,
      "ngpus_total": 32,
      "gpu": {
        "name": "NVIDIA A100-SXM4-40GB, CUDA v12.4",
        "memory_per_gpu_gib": 39,
        "gpu_memory_per_node_gib": 156,
        "total_gpu_memory_gib": 1248
      }
    },
    "system_info": {
      "nbf": 221,
      "nshells": 105,
      "nelectrons_total": 98,
      "nelectrons_alpha": 49,
      "nelectrons_beta": 49,
      "nbf_orig": 221
    },
    "SCF": {
      "nucl_rep_energy": 731.0227698813991,
      "xHF": 1.0,
      "iter": {
        "1": {
          "energy": -3011.0829400775233,
          "e_diff": -3011.0829400775233,
          "rmsd": 0.01642787817669442,
          "ediis": 1359.1055331057948,
          "performance": {
            "total_time": 0.195327312
          }
        },
        "2": {
          "energy": -3005.6271638574817,
          "e_diff": 5.455776220041571,
          "rmsd": 0.006841845733322585,
          "ediis": 11.271211523587873,
          "performance": {
            "total_time": 0.348678532
          }
        },
        "3": {
          "energy": -3005.967654810395,
          "e_diff": -0.3404909529131146,
          "rmsd": 0.0023667976083169475,
          "ediis": 3.0116354091319026,
          "performance": {
            "total_time": 0.350244039
          }
        },
        "4": {
          "energy": -3006.0563777348248,
          "e_diff": -0.08872292442993057,
          "rmsd": 0.0013074296010482643,
          "ediis": 0.11165902411690956,
          "performance": {
            "total_time": 0.354670098
          }
        },
        "5": {
          "energy": -3006.063783334415,
          "e_diff": -0.007405599590128986,
          "rmsd": 0.00039851238189219534,
          "ediis": 0.017464346906617575,
          "performance": {
            "total_time": 0.376773414
          }
        },
        "6": {
          "energy": -3006.064892156569,
          "e_diff": -0.0011088221540376253,
          "rmsd": 0.00031163099246067167,
          "ediis": 0.003321968217326633,
          "performance": {
            "total_time": 0.368158107
          }
        },
        "7": {
          "energy": -3006.0652537722444,
          "e_diff": -0.0003616156755015254,
          "rmsd": 0.0001327987495049606,
          "ediis": 0.0005057864628958892,
          "performance": {
            "total_time": 0.370439788
          }
        },
        "8": {
          "energy": -3006.0653153936755,
          "e_diff": -6.162143108667806e-05,
          "rmsd": 3.057327838451806e-05,
          "ediis": 7.20476243477652e-05,
          "performance": {
            "total_time": 0.380788809
          }
        },
        "9": {
          "energy": -3006.0653230311514,
          "e_diff": -7.637475846422603e-06,
          "rmsd": 1.4691554838694297e-05,
          "ediis": 1.8090466880335866e-05,
          "performance": {
            "total_time": 0.399809787
          }
        },
        "10": {
          "energy": -3006.0653252248885,
          "e_diff": -2.193737145717023e-06,
          "rmsd": 7.77388324600587e-06,
          "ediis": 3.4294770609968216e-06,
          "performance": {
            "total_time": 0.403613932
          }
        },
        "11": {
          "energy": -3006.0653257342788,
          "e_diff": -5.093902473163325e-07,
          "rmsd": 3.397728877416528e-06,
          "ediis": 5.973002465799383e-07,
          "performance": {
            "total_time": 0.439785712
          }
        },
        "12": {
          "energy": -3006.0653258132584,
          "e_diff": -7.897961040725932e-08,
          "rmsd": 1.5415010906679457e-06,
          "ediis": 9.413770636531465e-08,
          "performance": {
            "total_time": 0.425247901
          }
        },
        "13": {
          "energy": -3006.0653258269062,
          "e_diff": -1.3647877494804561e-08,
          "rmsd": 6.824145048941251e-07,
          "ediis": 1.8893269418407994e-08,
          "performance": {
            "total_time": 0.430073994
          }
        },
        "14": {
          "energy": -3006.065325829726,
          "e_diff": -2.819888322846964e-09,
          "rmsd": 3.110168175941138e-07,
          "ediis": 5.940819596745242e-09,
          "performance": {
            "total_time": 0.455167633
          }
        },
        "15": {
          "energy": -3006.0653258306306,
          "e_diff": -9.044924809131771e-10,
          "rmsd": 2.5349956346348885e-07,
          "ediis": 2.468660435064299e-09,
          "performance": {
            "total_time": 0.426799743
          }
        },
        "16": {
          "energy": -3006.0653258311513,
          "e_diff": -5.206857167650014e-10,
          "rmsd": 1.8231265304500922e-07,
          "ediis": 8.797936954289093e-10,
          "performance": {
            "total_time": 0.435737183
          }
        },
        "17": {
          "energy": -3006.0653258313732,
          "e_diff": -2.219167072325945e-10,
          "rmsd": 9.582043333231467e-08,
          "ediis": 2.720994028673108e-10,
          "performance": {
            "total_time": 0.428792636
          }
        },
        "18": {
          "energy": -3006.0653258314305,
          "e_diff": -5.729816621169448e-11,
          "rmsd": 5.473486695940748e-08,
          "ediis": 8.23228069158238e-11,
          "performance": {
            "total_time": 0.438522459
          }
        },
        "19": {
          "energy": -3006.06532583145,
          "e_diff": -1.9554136088117957e-11,
          "rmsd": 2.9469441743000833e-08,
          "ediis": 2.130189320705969e-11,
          "performance": {
            "total_time": 0.427656288
          }
        },
        "20": {
          "energy": -3006.065325831454,
          "e_diff": -4.092726157978177e-12,
          "rmsd": 1.1432825968962532e-08,
          "ediis": 4.758152039179693e-12,
          "performance": {
            "total_time": 0.438518431
          }
        },
        "21": {
          "energy": -3006.0653258314514,
          "e_diff": 2.7284841053187847e-12,
          "rmsd": 6.32863707066931e-09,
          "ediis": 1.613109525371052e-12,
          "performance": {
            "total_time": 0.424763685
          }
        }
      },
      "NE_1e": -8614.516185368511,
      "kinetic_1e": 3005.562515226311,
      "energy_1e": -5599.8063560482115,
      "energy_2e": 1871.6550702774937,
      "energy_qed": 0.21050415185526816,
      "energy_qed_et": -37.37088095712852,
      "final_energy": -3006.0653258314514,
      "n_iterations": 21,
      "performance": {
        "total_time": 12.360540384
      }
    },
    "CD": {
      "n_cholesky_vectors": 1241,
      "diagtol": 1e-05
    },
    "CCSD": {
      "iter": {
        "1": {
          "residual": 1.1807954772505511,
          "correlation": 0.0,
          "performance": {
            "total_time": 29.52676891
          }
        },
        "2": {
          "residual": 0.1851347253351672,
          "correlation": -1.5748241060598611,
          "performance": {
            "total_time": 28.573909997
          }
        },
        "3": {
          "residual": 0.07036546251463718,
          "correlation": -1.6273163714090981,
          "performance": {
            "total_time": 28.625212804
          }
        },
        "4": {
          "residual": 0.03034275106032149,
          "correlation": -1.6957938020102383,
          "performance": {
            "total_time": 28.452824485
          }
        },
        "5": {
          "residual": 0.022799480709262,
          "correlation": -1.6930733112820218,
          "performance": {
            "total_time": 28.384852611
          }
        },
        "6": {
          "residual": 0.012391981533591438,
          "correlation": -1.706797762664398,
          "performance": {
            "total_time": 28.304441143
          }
        },
        "7": {
          "residual": 0.008279885300676368,
          "correlation": -1.70610870327673,
          "performance": {
            "total_time": 28.111943661
          }
        },
        "8": {
          "residual": 0.0071773943308638686,
          "correlation": -1.708066733929388,
          "performance": {
            "total_time": 28.143255083
          }
        },
        "9": {
          "residual": 0.007832918996252113,
          "correlation": -1.7086017301290872,
          "performance": {
            "total_time": 28.286396575
          }
        },
        "10": {
          "residual": 0.010501969359197848,
          "correlation": -1.7090363251914547,
          "performance": {
            "total_time": 28.246713077
          }
        },
        "11": {
          "residual": 0.0014858765881746335,
          "correlation": -1.7102523205849325,
          "performance": {
            "total_time": 28.393854283
          }
        },
        "12": {
          "residual": 0.0009763376113301735,
          "correlation": -1.7100558272417803,
          "performance": {
            "total_time": 28.352686945
          }
        },
        "13": {
          "residual": 0.0010469376196367113,
          "correlation": -1.7103410656105207,
          "performance": {
            "total_time": 28.223762794
          }
        },
        "14": {
          "residual": 0.0016617462338198346,
          "correlation": -1.710235757222663,
          "performance": {
            "total_time": 28.236610723
          }
        },
        "15": {
          "residual": 0.002827908559972114,
          "correlation": -1.7103429170410565,
          "performance": {
            "total_time": 28.446845511
          }
        },
        "16": {
          "residual": 0.0002138284004897058,
          "correlation": -1.7103851446671863,
          "performance": {
            "total_time": 28.501080948
          }
        },
        "17": {
          "residual": 0.00014881468477883567,
          "correlation": -1.7103262731279907,
          "performance": {
            "total_time": 28.635587633
          }
        },
        "18": {
          "residual": 0.00016308374682245176,
          "correlation": -1.7103565024281226,
          "performance": {
            "total_time": 28.248416769
          }
        },
        "19": {
          "residual": 0.00024147460253733666,
          "correlation": -1.7103605518283305,
          "performance": {
            "total_time": 28.531122224
          }
        },
        "20": {
          "residual": 0.0003822333830477615,
          "correlation": -1.7103668993572327,
          "performance": {
            "total_time": 28.311444969
          }
        },
        "21": {
          "residual": 3.866076134975172e-05,
          "correlation": -1.710383929491464,
          "performance": {
            "total_time": 28.332869234
          }
        },
        "22": {
          "residual": 2.4998880707099744e-05,
          "correlation": -1.7103814753655453,
          "performance": {
            "total_time": 28.290167196
          }
        },
        "23": {
          "residual": 2.520847668442558e-05,
          "correlation": -1.7103864036979797,
          "performance": {
            "total_time": 28.381428073
          }
        },
        "24": {
          "residual": 3.5493488174104846e-05,
          "correlation": -1.7103843120701694,
          "performance": {
            "total_time": 28.233703238
          }
        },
        "25": {
          "residual": 5.86120973353759e-05,
          "correlation": -1.7103859488340176,
          "performance": {
            "total_time": 28.977244868
          }
        },
        "26": {
          "residual": 8.04048857214549e-06,
          "correlation": -1.710386680509673,
          "performance": {
            "total_time": 28.385235174
          }
        },
        "27": {
          "residual": 5.883294186232026e-06,
          "correlation": -1.7103852977378367,
          "performance": {
            "total_time": 28.385845544
          }
        },
        "28": {
          "residual": 6.906301972810452e-06,
          "correlation": -1.7103860503354584,
          "performance": {
            "total_time": 28.30831993
          }
        },
        "29": {
          "residual": 1.0585037238156965e-05,
          "correlation": -1.7103861514826917,
          "performance": {
            "total_time": 28.464939996
          }
        },
        "30": {
          "residual": 1.6862583460227424e-05,
          "correlation": -1.7103863106518562,
          "performance": {
            "total_time": 28.56587161
          }
        },
        "31": {
          "residual": 2.0682104540718525e-06,
          "correlation": -1.710387021692308,
          "performance": {
            "total_time": 28.405307767
          }
        },
        "32": {
          "residual": 1.4290501022305294e-06,
          "correlation": -1.7103867517088218,
          "performance": {
            "total_time": 28.503940901
          }
        },
        "33": {
          "residual": 1.2993847820633499e-06,
          "correlation": -1.7103868772345454,
          "performance": {
            "total_time": 28.509555649
          }
        },
        "34": {
          "residual": 1.7321368995368315e-06,
          "correlation": -1.7103867491424718,
          "performance": {
            "total_time": 28.438376779
          }
        },
        "35": {
          "residual": 2.797294089221363e-06,
          "correlation": -1.71038679197862,
          "performance": {
            "total_time": 28.769117529
          }
        },
        "36": {
          "residual": 5.051452221554334e-07,
          "correlation": -1.7103867422660421,
          "performance": {
            "total_time": 28.854771841
          }
        }
      },
      "n_iterations": 36,
      "final_energy": {
        "correlation": -1.7103867422660421,
        "total": -3007.7757125737176
      },
      "performance": {
        "total_time": 1042.002080721
      }
    }
  },
  "molecule": {
    "name": "para_theta_101.73913043478261_phi_172.17391304347825",
    "basis": {
      "basisset": "6-311G*"
    },
    "nbf": 221,
    "nshells": 105,
    "nelectrons": 98,
    "nelectrons_alpha": 49,
    "nelectrons_beta": 49
  },
  "input": {
    "geometry": {
      "coordinates": [
        "C                 -0.80658313    1.22973465    0.03041801",
        "C                  0.56153576    1.23725234    0.01622618",
        "C                  1.22915389    0.01001055    0.01220575",
        "H                 -1.36676923    2.15803094    0.04420367",
        "H                  1.14116413    2.14927050    0.01037697",
        "N                  2.71357475    0.03144573   -0.00289824",
        "O                  3.28013247   -1.09741954   -0.00254733",
        "O                  3.24714953    1.17621948   -0.01252002",
        "C                 -0.77042978   -1.26805414    0.04039660",
        "H                 -1.30353926   -2.21202933    0.06122375",
        "C                  0.59726287   -1.23605918    0.02634378",
        "H                  1.20308359   -2.13089607    0.02793117",
        "C                 -1.56287141   -0.03049318    0.01040538",
        "H                 -2.41148563   -0.03994459    0.70143946",
        "Br                -2.40993182   -0.04931830   -1.82359612"
      ],
      "units": "angstrom"
    },
    "basis": {
      "basisset": "6-311G*"
    },
    "SCF": {
      "charge": 1,
      "multiplicity": 1,
      "conve": 1e-10,
      "convd": 1e-08,
      "scf_type": "restricted",
      "qed_omegas": [
        0.06614874648125418
      ],
      "qed_volumes": [],
      "qed_lambdas": [
        0.1
      ],
      "qed_polvecs": [
        [
          -0.9699648456546799,
          0.13331859940315766,
          -0.20345601305263386
        ]
      ]
    },
    "CC": {
      "threshold": 1e-06,
      "lshift": 0.0,
      "ccsd_maxiter": 200,
      "freeze": {
        "atomic": true
      }
    },
    "TASK": {
      "ccsd": true
    }
  }
}
