{
  "output": {
    "machine_info": {
      "date": "Sun Sep 21 12:04:21 2025",
      "nnodes": 8,
      "nproc_per_node": 4,
      "nproc_total": 32,
      "cpu": {
        "name": "AMD EPYC 7763 64-Core Processor                ",
        "cpu_memory_per_node_gib": 251,
        "total_cpu_memory_gib": 2008
      },
      "ngpus_per_node": 4,
      "ngpus_total": 32,
      "gpu": {
        "name": "NVIDIA A100-SXM4-40GB, CUDA v12.4",
        "memory_per_gpu_gib": 39,
        "gpu_memory_per_node_gib": 156,
        "total_gpu_memory_gib": 1248
      }
    },
    "system_info": {
      "nbf": 221,
      "nshells": 105,
      "nelectrons_total": 98,
      "nelectrons_alpha": 49,
      "nelectrons_beta": 49,
      "nbf_orig": 221
    },
    "SCF": {
      "nucl_rep_energy": 731.0227698813991,
      "xHF": 1.0,
      "iter": {
        "1": {
          "energy": -3011.1772555105285,
          "e_diff": -3011.1772555105285,
          "rmsd": 0.016417314987903508,
          "ediis": 1354.1841705187078,
          "performance": {
            "total_time": 0.188829091
          }
        },
        "2": {
          "energy": -3005.7827201739815,
          "e_diff": 5.394535336547051,
          "rmsd": 0.006770111787802327,
          "ediis": 8.104225818860392,
          "performance": {
            "total_time": 0.347398307
          }
        },
        "3": {
          "energy": -3005.9421767806793,
          "e_diff": -0.15945660669785866,
          "rmsd": 0.0028784634699410847,
          "ediis": 5.13954883838992,
          "performance": {
            "total_time": 0.355437969
          }
        },
        "4": {
          "energy": -3006.0896218301937,
          "e_diff": -0.14744504951431736,
          "rmsd": 0.001117571088935884,
          "ediis": 0.11596932453486233,
          "performance": {
            "total_time": 0.35334933
          }
        },
        "5": {
          "energy": -3006.095568429295,
          "e_diff": -0.005946599101207539,
          "rmsd": 0.0002699083381437989,
          "ediis": 0.014366273954872468,
          "performance": {
            "total_time": 0.36141902
          }
        },
        "6": {
          "energy": -3006.09622286193,
          "e_diff": -0.0006544326352013741,
          "rmsd": 0.00013670778861168997,
          "ediis": 0.001010862167297264,
          "performance": {
            "total_time": 0.36455589
          }
        },
        "7": {
          "energy": -3006.0963163773567,
          "e_diff": -9.351542666991008e-05,
          "rmsd": 5.3106225268831864e-05,
          "ediis": 0.00014492729053592788,
          "performance": {
            "total_time": 0.37269846
          }
        },
        "8": {
          "energy": -3006.0963319541065,
          "e_diff": -1.557674977448187e-05,
          "rmsd": 1.8535410755079612e-05,
          "ediis": 2.1924539538779423e-05,
          "performance": {
            "total_time": 0.383006788
          }
        },
        "9": {
          "energy": -3006.0963343468607,
          "e_diff": -2.3927541406010278e-06,
          "rmsd": 7.128065615122286e-06,
          "ediis": 2.9787201786368545e-06,
          "performance": {
            "total_time": 0.390512355
          }
        },
        "10": {
          "energy": -3006.096334752741,
          "e_diff": -4.058802005602047e-07,
          "rmsd": 2.518274815846565e-06,
          "ediis": 4.0204761008104267e-07,
          "performance": {
            "total_time": 0.40105155
          }
        },
        "11": {
          "energy": -3006.0963348023893,
          "e_diff": -4.964840627508238e-08,
          "rmsd": 1.0851441055759905e-06,
          "ediis": 9.949104566308893e-08,
          "performance": {
            "total_time": 0.448482224
          }
        },
        "12": {
          "energy": -3006.096334811306,
          "e_diff": -8.916686056181788e-09,
          "rmsd": 5.88066294170136e-07,
          "ediis": 2.3989502303830343e-08,
          "performance": {
            "total_time": 0.426808578
          }
        },
        "13": {
          "energy": -3006.096334813823,
          "e_diff": -2.517026587156579e-09,
          "rmsd": 3.299109874922384e-07,
          "ediis": 3.6986568859817064e-09,
          "performance": {
            "total_time": 0.436106268
          }
        },
        "14": {
          "energy": -3006.096334814459,
          "e_diff": -6.361915438901633e-10,
          "rmsd": 1.866797107224277e-07,
          "ediis": 6.755744636184567e-10,
          "performance": {
            "total_time": 0.423881726
          }
        },
        "15": {
          "energy": -3006.0963348146115,
          "e_diff": -1.5234036254696548e-10,
          "rmsd": 6.223316360641301e-08,
          "ediis": 1.4282267279997373e-10,
          "performance": {
            "total_time": 0.43107643
          }
        },
        "16": {
          "energy": -3006.0963348146397,
          "e_diff": -2.8194335754960775e-11,
          "rmsd": 3.0760358224155656e-08,
          "ediis": 3.274804198670919e-11,
          "performance": {
            "total_time": 0.430587022
          }
        },
        "17": {
          "energy": -3006.0963348146474,
          "e_diff": -7.73070496506989e-12,
          "rmsd": 2.125866389396829e-08,
          "ediis": 9.989283133023542e-12,
          "performance": {
            "total_time": 0.422117217
          }
        },
        "18": {
          "energy": -3006.0963348146506,
          "e_diff": -3.183231456205249e-12,
          "rmsd": 7.333872148551499e-09,
          "ediis": 1.6738341558340494e-12,
          "performance": {
            "total_time": 0.434294486
          }
        }
      },
      "NE_1e": -8614.626358065798,
      "kinetic_1e": 3005.5984795578206,
      "energy_1e": -5607.41076888871,
      "energy_2e": 1871.7261822991306,
      "energy_qed": 0.1825915127972706,
      "energy_qed_et": -37.37119104696051,
      "final_energy": -3006.0963348146506,
      "n_iterations": 18,
      "performance": {
        "total_time": 10.201097281
      }
    },
    "CD": {
      "n_cholesky_vectors": 1241,
      "diagtol": 1e-05
    },
    "CCSD": {
      "iter": {
        "1": {
          "residual": 1.1829713521053995,
          "correlation": 0.0,
          "performance": {
            "total_time": 29.632667249
          }
        },
        "2": {
          "residual": 0.1719857521710945,
          "correlation": -1.7120056055085577,
          "performance": {
            "total_time": 73.408998262
          }
        },
        "3": {
          "residual": 0.07327840055805676,
          "correlation": -1.6380008569283975,
          "performance": {
            "total_time": 30.88358498
          }
        },
        "4": {
          "residual": 0.024153041525091123,
          "correlation": -1.7190310448675363,
          "performance": {
            "total_time": 28.518529548
          }
        },
        "5": {
          "residual": 0.019308632671395293,
          "correlation": -1.7043068840129423,
          "performance": {
            "total_time": 30.231303344
          }
        },
        "6": {
          "residual": 0.007123089671892293,
          "correlation": -1.7159464147331556,
          "performance": {
            "total_time": 28.443722968
          }
        },
        "7": {
          "residual": 0.004445761556750812,
          "correlation": -1.7155948000700154,
          "performance": {
            "total_time": 28.329164966
          }
        },
        "8": {
          "residual": 0.0027196699069734005,
          "correlation": -1.716837080034435,
          "performance": {
            "total_time": 28.472409227
          }
        },
        "9": {
          "residual": 0.0019451681439774694,
          "correlation": -1.7168970412170552,
          "performance": {
            "total_time": 28.58149153
          }
        },
        "10": {
          "residual": 0.0017029499996828576,
          "correlation": -1.717180548993251,
          "performance": {
            "total_time": 28.517060393
          }
        },
        "11": {
          "residual": 0.0003572381234022445,
          "correlation": -1.7174774150705847,
          "performance": {
            "total_time": 28.440445048
          }
        },
        "12": {
          "residual": 0.00023000420201619928,
          "correlation": -1.717527891975555,
          "performance": {
            "total_time": 28.507782255
          }
        },
        "13": {
          "residual": 0.0001715283818079296,
          "correlation": -1.7175346184309344,
          "performance": {
            "total_time": 36.505860991
          }
        },
        "14": {
          "residual": 0.00014998355131413103,
          "correlation": -1.717523575185857,
          "performance": {
            "total_time": 28.431735242
          }
        },
        "15": {
          "residual": 0.0001318551970894475,
          "correlation": -1.717529801100882,
          "performance": {
            "total_time": 28.451911644
          }
        },
        "16": {
          "residual": 5.659022987804428e-05,
          "correlation": -1.7175141933713767,
          "performance": {
            "total_time": 28.458674695
          }
        },
        "17": {
          "residual": 3.5902159987844536e-05,
          "correlation": -1.717527388437972,
          "performance": {
            "total_time": 28.377517157
          }
        },
        "18": {
          "residual": 3.0478334462989604e-05,
          "correlation": -1.7175287008320883,
          "performance": {
            "total_time": 28.294074084
          }
        },
        "19": {
          "residual": 2.276991788133644e-05,
          "correlation": -1.7175311658384034,
          "performance": {
            "total_time": 40.524741039
          }
        },
        "20": {
          "residual": 2.1731904025474152e-05,
          "correlation": -1.717530741319184,
          "performance": {
            "total_time": 28.572257081
          }
        },
        "21": {
          "residual": 8.559950896182091e-06,
          "correlation": -1.7175325611803196,
          "performance": {
            "total_time": 28.873136755
          }
        },
        "22": {
          "residual": 5.801419787981728e-06,
          "correlation": -1.7175326757042335,
          "performance": {
            "total_time": 28.702567156
          }
        },
        "23": {
          "residual": 4.148850766532427e-06,
          "correlation": -1.7175326447126744,
          "performance": {
            "total_time": 28.569429546
          }
        },
        "24": {
          "residual": 3.7901030774506948e-06,
          "correlation": -1.7175321353002087,
          "performance": {
            "total_time": 28.883526566
          }
        },
        "25": {
          "residual": 3.172182464156852e-06,
          "correlation": -1.717532309585551,
          "performance": {
            "total_time": 28.711660899
          }
        },
        "26": {
          "residual": 1.4310447272274604e-06,
          "correlation": -1.7175316222251802,
          "performance": {
            "total_time": 28.773070858
          }
        },
        "27": {
          "residual": 8.784844501732334e-07,
          "correlation": -1.717532097969009,
          "performance": {
            "total_time": 28.55658502
          }
        }
      },
      "n_iterations": 27,
      "final_energy": {
        "correlation": -1.717532097969009,
        "total": -3007.8138669126197
      },
      "performance": {
        "total_time": 853.796505161
      }
    }
  },
  "molecule": {
    "name": "para_theta_180.0_phi_219.1304347826087",
    "basis": {
      "basisset": "6-311G*"
    },
    "nbf": 221,
    "nshells": 105,
    "nelectrons": 98,
    "nelectrons_alpha": 49,
    "nelectrons_beta": 49
  },
  "input": {
    "geometry": {
      "coordinates": [
        "C                 -0.80658313    1.22973465    0.03041801",
        "C                  0.56153576    1.23725234    0.01622618",
        "C                  1.22915389    0.01001055    0.01220575",
        "H                 -1.36676923    2.15803094    0.04420367",
        "H                  1.14116413    2.14927050    0.01037697",
        "N                  2.71357475    0.03144573   -0.00289824",
        "O                  3.28013247   -1.09741954   -0.00254733",
        "O                  3.24714953    1.17621948   -0.01252002",
        "C                 -0.77042978   -1.26805414    0.04039660",
        "H                 -1.30353926   -2.21202933    0.06122375",
        "C                  0.59726287   -1.23605918    0.02634378",
        "H                  1.20308359   -2.13089607    0.02793117",
        "C                 -1.56287141   -0.03049318    0.01040538",
        "H                 -2.41148563   -0.03994459    0.70143946",
        "Br                -2.40993182   -0.04931830   -1.82359612"
      ],
      "units": "angstrom"
    },
    "basis": {
      "basisset": "6-311G*"
    },
    "SCF": {
      "charge": 1,
      "multiplicity": 1,
      "conve": 1e-10,
      "convd": 1e-08,
      "scf_type": "restricted",
      "qed_omegas": [
        0.06614874648125418
      ],
      "qed_volumes": [],
      "qed_lambdas": [
        0.1
      ],
      "qed_polvecs": [
        [
          -9.499723492236297e-17,
          -7.728598309993836e-17,
          -1.0
        ]
      ]
    },
    "CC": {
      "threshold": 1e-06,
      "lshift": 0.0,
      "ccsd_maxiter": 200,
      "freeze": {
        "atomic": true
      }
    },
    "TASK": {
      "ccsd": true
    }
  }
}
