{
  "output": {
    "machine_info": {
      "date": "Sun Sep 21 08:57:56 2025",
      "nnodes": 8,
      "nproc_per_node": 4,
      "nproc_total": 32,
      "cpu": {
        "name": "AMD EPYC 7763 64-Core Processor                ",
        "cpu_memory_per_node_gib": 251,
        "total_cpu_memory_gib": 2008
      },
      "ngpus_per_node": 4,
      "ngpus_total": 32,
      "gpu": {
        "name": "NVIDIA A100-SXM4-40GB, CUDA v12.4",
        "memory_per_gpu_gib": 39,
        "gpu_memory_per_node_gib": 156,
        "total_gpu_memory_gib": 1248
      }
    },
    "system_info": {
      "nbf": 221,
      "nshells": 105,
      "nelectrons_total": 98,
      "nelectrons_alpha": 49,
      "nelectrons_beta": 49,
      "nbf_orig": 221
    },
    "SCF": {
      "nucl_rep_energy": 772.8921057975059,
      "xHF": 1.0,
      "iter": {
        "1": {
          "energy": -3011.2817645582763,
          "e_diff": -3011.2817645582763,
          "rmsd": 0.016399925362274456,
          "ediis": 1348.9859241495858,
          "performance": {
            "total_time": 0.184504273
          }
        },
        "2": {
          "energy": -3005.717829076771,
          "e_diff": 5.563935481505268,
          "rmsd": 0.007222010415790839,
          "ediis": 8.41420917383902,
          "performance": {
            "total_time": 0.348451553
          }
        },
        "3": {
          "energy": -3005.9143976364226,
          "e_diff": -0.1965685596514959,
          "rmsd": 0.003112591218694869,
          "ediis": 4.731356935018714,
          "performance": {
            "total_time": 0.349303214
          }
        },
        "4": {
          "energy": -3006.053322087719,
          "e_diff": -0.1389244512965888,
          "rmsd": 0.001297876938551855,
          "ediis": 0.16219890984374424,
          "performance": {
            "total_time": 0.355942251
          }
        },
        "5": {
          "energy": -3006.062226618763,
          "e_diff": -0.008904531043754105,
          "rmsd": 0.0003038264201995103,
          "ediis": 0.013175814929753971,
          "performance": {
            "total_time": 0.372604255
          }
        },
        "6": {
          "energy": -3006.0629826165077,
          "e_diff": -0.0007559977448181598,
          "rmsd": 0.0001873637766142631,
          "ediis": 0.001978213228006827,
          "performance": {
            "total_time": 0.368461415
          }
        },
        "7": {
          "energy": -3006.063198800881,
          "e_diff": -0.00021618437313009053,
          "rmsd": 7.831482486202438e-05,
          "ediis": 0.0006066930681455677,
          "performance": {
            "total_time": 0.374520659
          }
        },
        "8": {
          "energy": -3006.063263770482,
          "e_diff": -6.496960122603923e-05,
          "rmsd": 5.048326016365614e-05,
          "ediis": 0.00018198714301276915,
          "performance": {
            "total_time": 0.393794045
          }
        },
        "9": {
          "energy": -3006.0632855474078,
          "e_diff": -2.1776925677841064e-05,
          "rmsd": 2.8140594168949757e-05,
          "ediis": 2.336587133315554e-05,
          "performance": {
            "total_time": 0.391280963
          }
        },
        "10": {
          "energy": -3006.063290331829,
          "e_diff": -4.784421435033437e-06,
          "rmsd": 1.1069484884391474e-05,
          "ediis": 4.959854618819474e-06,
          "performance": {
            "total_time": 0.398615178
          }
        },
        "11": {
          "energy": -3006.0632910095096,
          "e_diff": -6.776804184482899e-07,
          "rmsd": 5.540824255035429e-06,
          "ediis": 8.253926927307906e-07,
          "performance": {
            "total_time": 0.4288449
          }
        },
        "12": {
          "energy": -3006.063291175892,
          "e_diff": -1.663825059949886e-07,
          "rmsd": 2.9264121033163046e-06,
          "ediis": 2.433877383226347e-07,
          "performance": {
            "total_time": 0.422667837
          }
        },
        "13": {
          "energy": -3006.063291224156,
          "e_diff": -4.8263700591633096e-08,
          "rmsd": 1.777447896790306e-06,
          "ediis": 6.134901351536126e-08,
          "performance": {
            "total_time": 0.422402553
          }
        },
        "14": {
          "energy": -3006.0632912387573,
          "e_diff": -1.4601482689613476e-08,
          "rmsd": 6.616842660067773e-07,
          "ediis": 1.0896241005757632e-08,
          "performance": {
            "total_time": 0.425334476
          }
        },
        "15": {
          "energy": -3006.063291241124,
          "e_diff": -2.3665052140131593e-09,
          "rmsd": 3.0713705352822974e-07,
          "ediis": 2.7341039925077636e-09,
          "performance": {
            "total_time": 0.437008642
          }
        },
        "16": {
          "energy": -3006.063291241565,
          "e_diff": -4.411049303598702e-10,
          "rmsd": 1.527508748895681e-07,
          "ediis": 4.938395944027815e-10,
          "performance": {
            "total_time": 0.428349951
          }
        },
        "17": {
          "energy": -3006.0632912416577,
          "e_diff": -9.276845958083868e-11,
          "rmsd": 6.318616974172322e-08,
          "ediis": 1.0672817874635572e-10,
          "performance": {
            "total_time": 0.421496818
          }
        },
        "18": {
          "energy": -3006.0632912416727,
          "e_diff": -1.5006662579253316e-11,
          "rmsd": 2.8426449322030187e-08,
          "ediis": 2.5738540716203254e-11,
          "performance": {
            "total_time": 0.431880583
          }
        },
        "19": {
          "energy": -3006.0632912416763,
          "e_diff": -3.637978807091713e-12,
          "rmsd": 1.9948154765197343e-08,
          "ediis": 1.1377090861687739e-11,
          "performance": {
            "total_time": 0.420467924
          }
        },
        "20": {
          "energy": -3006.0632912416786,
          "e_diff": -2.2737367544323206e-12,
          "rmsd": 9.044372409060175e-09,
          "ediis": 2.4029329707866217e-12,
          "performance": {
            "total_time": 0.42212727
          }
        }
      },
      "NE_1e": -8698.477817041019,
      "kinetic_1e": 3005.6049618993065,
      "energy_1e": -5689.976597706658,
      "energy_2e": 1913.6940638322087,
      "energy_qed": 0.22339427032052583,
      "energy_qed_et": -37.78955397039185,
      "final_energy": -3006.0632912416786,
      "n_iterations": 20,
      "performance": {
        "total_time": 11.523168097
      }
    },
    "CD": {
      "n_cholesky_vectors": 1235,
      "diagtol": 1e-05
    },
    "CCSD": {
      "iter": {
        "1": {
          "residual": 1.1846870167545929,
          "correlation": 0.0,
          "performance": {
            "total_time": 29.420465783
          }
        },
        "2": {
          "residual": 0.1878685921030219,
          "correlation": -1.7165344244537568,
          "performance": {
            "total_time": 28.557923904
          }
        },
        "3": {
          "residual": 0.09827510528933549,
          "correlation": -1.6367047270653232,
          "performance": {
            "total_time": 28.533836334
          }
        },
        "4": {
          "residual": 0.0479621199699854,
          "correlation": -1.753107437080227,
          "performance": {
            "total_time": 28.603056989
          }
        },
        "5": {
          "residual": 0.043369422609708656,
          "correlation": -1.710628960782072,
          "performance": {
            "total_time": 28.870158454
          }
        },
        "6": {
          "residual": 0.01009677239615649,
          "correlation": -1.7370702144253074,
          "performance": {
            "total_time": 28.341755884
          }
        },
        "7": {
          "residual": 0.006754491458300235,
          "correlation": -1.735898535213144,
          "performance": {
            "total_time": 28.399431298
          }
        },
        "8": {
          "residual": 0.004234698006756907,
          "correlation": -1.7388035348378958,
          "performance": {
            "total_time": 28.460593157999998
          }
        },
        "9": {
          "residual": 0.0033617794388060103,
          "correlation": -1.7383476163122444,
          "performance": {
            "total_time": 28.469755559
          }
        },
        "10": {
          "residual": 0.003296988159846198,
          "correlation": -1.739344942102861,
          "performance": {
            "total_time": 28.602399912
          }
        },
        "11": {
          "residual": 0.0007510665035951302,
          "correlation": -1.7397374682528604,
          "performance": {
            "total_time": 29.068079597
          }
        },
        "12": {
          "residual": 0.0005196955038944816,
          "correlation": -1.7398836707241017,
          "performance": {
            "total_time": 28.656381899
          }
        },
        "13": {
          "residual": 0.00037463841031321586,
          "correlation": -1.7398609761855386,
          "performance": {
            "total_time": 28.475755524
          }
        },
        "14": {
          "residual": 0.00030683538546638146,
          "correlation": -1.7398606843725057,
          "performance": {
            "total_time": 28.419715701
          }
        },
        "15": {
          "residual": 0.00023612878629997636,
          "correlation": -1.7398749403419673,
          "performance": {
            "total_time": 28.527889441
          }
        },
        "16": {
          "residual": 0.00011131236826342687,
          "correlation": -1.7398731279239668,
          "performance": {
            "total_time": 28.457541452
          }
        },
        "17": {
          "residual": 7.794099140067498e-05,
          "correlation": -1.7398779934356108,
          "performance": {
            "total_time": 28.756191112
          }
        },
        "18": {
          "residual": 6.225664512698002e-05,
          "correlation": -1.7398967573364414,
          "performance": {
            "total_time": 28.546686183
          }
        },
        "19": {
          "residual": 5.105874787386491e-05,
          "correlation": -1.7398936665678681,
          "performance": {
            "total_time": 28.390645182
          }
        },
        "20": {
          "residual": 4.973166845813857e-05,
          "correlation": -1.73990127641327,
          "performance": {
            "total_time": 28.369398024
          }
        },
        "21": {
          "residual": 2.0002721251222757e-05,
          "correlation": -1.7399055984813805,
          "performance": {
            "total_time": 28.419436424
          }
        },
        "22": {
          "residual": 1.3953770075127875e-05,
          "correlation": -1.7399066752597745,
          "performance": {
            "total_time": 28.526999579
          }
        },
        "23": {
          "residual": 1.1313339887024982e-05,
          "correlation": -1.7399038561165288,
          "performance": {
            "total_time": 28.502447467
          }
        },
        "24": {
          "residual": 1.005750702642202e-05,
          "correlation": -1.739904405550563,
          "performance": {
            "total_time": 28.815242413
          }
        },
        "25": {
          "residual": 1.0077034658933562e-05,
          "correlation": -1.7399034065576369,
          "performance": {
            "total_time": 28.526935288
          }
        },
        "26": {
          "residual": 3.5860704827776073e-06,
          "correlation": -1.7399026656020917,
          "performance": {
            "total_time": 28.429642698
          }
        },
        "27": {
          "residual": 2.614264596927358e-06,
          "correlation": -1.7399032854452452,
          "performance": {
            "total_time": 28.504042828
          }
        },
        "28": {
          "residual": 2.0687044940172576e-06,
          "correlation": -1.7399038262157775,
          "performance": {
            "total_time": 28.584441119
          }
        },
        "29": {
          "residual": 1.8537005776711813e-06,
          "correlation": -1.7399037447971921,
          "performance": {
            "total_time": 28.479119569
          }
        },
        "30": {
          "residual": 1.6617512691711225e-06,
          "correlation": -1.7399040225634141,
          "performance": {
            "total_time": 28.402502443
          }
        },
        "31": {
          "residual": 7.681346828132932e-07,
          "correlation": -1.7399041915393985,
          "performance": {
            "total_time": 28.466317802
          }
        }
      },
      "n_iterations": 31,
      "final_energy": {
        "correlation": -1.7399041915393985,
        "total": -3007.803195433218
      },
      "performance": {
        "total_time": 901.099058066
      }
    }
  },
  "molecule": {
    "name": "ortho_theta_93.91304347826087_phi_93.91304347826087",
    "basis": {
      "basisset": "6-311G*"
    },
    "nbf": 221,
    "nshells": 105,
    "nelectrons": 98,
    "nelectrons_alpha": 49,
    "nelectrons_beta": 49
  },
  "input": {
    "geometry": {
      "coordinates": [
        "C                  0.51932475    1.23303451   -0.03194925",
        "C                  1.94454413    1.26916358   -0.03672882",
        "C                  2.62037793    0.09283428   -0.02499003",
        "C                 -0.19603352    0.03013062    0.00102732",
        "H                 -0.02069420    2.17423764   -0.04336646",
        "H                  2.48281698    2.20891057   -0.03611879",
        "H                 -1.27770137    0.03990295    0.01166953",
        "N                  4.09213475    0.09594076    0.03662979",
        "O                  4.63930696   -1.02169275    0.14459220",
        "O                  4.66489883    1.19839699   -0.02327545",
        "C                  0.49428518   -1.16712649    0.02099746",
        "H                 -0.03251071   -2.11492669    0.05447935",
        "C                  1.96291176   -1.21653219   -0.02111314",
        "H                  2.44359113   -1.96306433    0.61513886",
        "Br                 2.17304025   -1.94912156   -1.90618750"
      ],
      "units": "angstrom"
    },
    "basis": {
      "basisset": "6-311G*"
    },
    "SCF": {
      "charge": 1,
      "multiplicity": 1,
      "conve": 1e-10,
      "convd": 1e-08,
      "scf_type": "restricted",
      "qed_omegas": [
        0.06614874648125418
      ],
      "qed_volumes": [],
      "qed_lambdas": [
        0.1
      ],
      "qed_polvecs": [
        [
          -0.06808332454812342,
          0.9953429730181653,
          -0.0682424133646711
        ]
      ]
    },
    "CC": {
      "threshold": 1e-06,
      "lshift": 0.0,
      "ccsd_maxiter": 200,
      "freeze": {
        "atomic": true
      }
    },
    "TASK": {
      "ccsd": true
    }
  }
}
