{
  "output": {
    "machine_info": {
      "date": "Sun Sep 21 13:06:06 2025",
      "nnodes": 8,
      "nproc_per_node": 4,
      "nproc_total": 32,
      "cpu": {
        "name": "AMD EPYC 7763 64-Core Processor                ",
        "cpu_memory_per_node_gib": 251,
        "total_cpu_memory_gib": 2008
      },
      "ngpus_per_node": 4,
      "ngpus_total": 32,
      "gpu": {
        "name": "NVIDIA A100-SXM4-40GB, CUDA v12.4",
        "memory_per_gpu_gib": 39,
        "gpu_memory_per_node_gib": 156,
        "total_gpu_memory_gib": 1248
      }
    },
    "system_info": {
      "nbf": 221,
      "nshells": 105,
      "nelectrons_total": 98,
      "nelectrons_alpha": 49,
      "nelectrons_beta": 49,
      "nbf_orig": 221
    },
    "SCF": {
      "nucl_rep_energy": 772.8921057975059,
      "xHF": 1.0,
      "iter": {
        "1": {
          "energy": -3011.4270473154893,
          "e_diff": -3011.4270473154893,
          "rmsd": 0.016470465343995717,
          "ediis": 1354.8551102614713,
          "performance": {
            "total_time": 0.190394783
          }
        },
        "2": {
          "energy": -3005.706278878461,
          "e_diff": 5.720768437028255,
          "rmsd": 0.007124996415295104,
          "ediis": 8.691940186748008,
          "performance": {
            "total_time": 0.348881694
          }
        },
        "3": {
          "energy": -3005.9291003361127,
          "e_diff": -0.22282145765166206,
          "rmsd": 0.0030555695451252025,
          "ediis": 4.478541206072721,
          "performance": {
            "total_time": 0.353714103
          }
        },
        "4": {
          "energy": -3006.0591243037975,
          "e_diff": -0.1300239676847923,
          "rmsd": 0.0013312301531075558,
          "ediis": 0.20272095568401513,
          "performance": {
            "total_time": 0.353816972
          }
        },
        "5": {
          "energy": -3006.0698319836765,
          "e_diff": -0.010707679879033094,
          "rmsd": 0.0004022618316798006,
          "ediis": 0.026744259028372668,
          "performance": {
            "total_time": 0.36086271599999997
          }
        },
        "6": {
          "energy": -3006.0712020947467,
          "e_diff": -0.0013701110701731523,
          "rmsd": 0.00021097427786319868,
          "ediis": 0.0038787103430292726,
          "performance": {
            "total_time": 0.366277272
          }
        },
        "7": {
          "energy": -3006.0715627761465,
          "e_diff": -0.00036068139979761327,
          "rmsd": 0.00012635926051794027,
          "ediis": 0.0011316737886426116,
          "performance": {
            "total_time": 0.374610651
          }
        },
        "8": {
          "energy": -3006.071705662956,
          "e_diff": -0.0001428868094990321,
          "rmsd": 7.238207037694304e-05,
          "ediis": 0.0002666373902992269,
          "performance": {
            "total_time": 0.381827978
          }
        },
        "9": {
          "energy": -3006.071748338478,
          "e_diff": -4.26755218541075e-05,
          "rmsd": 3.899860090285301e-05,
          "ediis": 4.942410665567198e-05,
          "performance": {
            "total_time": 0.399176385
          }
        },
        "10": {
          "energy": -3006.071758194579,
          "e_diff": -9.856101314653642e-06,
          "rmsd": 1.6499995154036984e-05,
          "ediis": 1.0007788170266573e-05,
          "performance": {
            "total_time": 0.403520959
          }
        },
        "11": {
          "energy": -3006.0717597404223,
          "e_diff": -1.5458431334991474e-06,
          "rmsd": 6.539905316921515e-06,
          "ediis": 1.6391022524492049e-06,
          "performance": {
            "total_time": 0.462222522
          }
        },
        "12": {
          "energy": -3006.071760053162,
          "e_diff": -3.127397576463409e-07,
          "rmsd": 3.4608685334668484e-06,
          "ediis": 5.59924085662267e-07,
          "performance": {
            "total_time": 0.423690249
          }
        },
        "13": {
          "energy": -3006.0717601535016,
          "e_diff": -1.0033954822574742e-07,
          "rmsd": 2.6169584777388835e-06,
          "ediis": 1.794020971549654e-07,
          "performance": {
            "total_time": 0.423885799
          }
        },
        "14": {
          "energy": -3006.0717601946985,
          "e_diff": -4.1196926758857444e-08,
          "rmsd": 1.3173579462547725e-06,
          "ediis": 4.27280074699149e-08,
          "performance": {
            "total_time": 0.473816415
          }
        },
        "15": {
          "energy": -3006.0717602040904,
          "e_diff": -9.391897037858143e-09,
          "rmsd": 6.349127498543843e-07,
          "ediis": 9.81621111566779e-09,
          "performance": {
            "total_time": 0.422055874
          }
        },
        "16": {
          "energy": -3006.071760205554,
          "e_diff": -1.4633769751526415e-09,
          "rmsd": 1.4786636057645734e-07,
          "ediis": 1.1788816192453531e-09,
          "performance": {
            "total_time": 0.427419662
          }
        },
        "17": {
          "energy": -3006.071760205658,
          "e_diff": -1.0413714335300028e-10,
          "rmsd": 6.587443121566879e-08,
          "ediis": 2.3582232265769803e-10,
          "performance": {
            "total_time": 0.428620598
          }
        },
        "18": {
          "energy": -3006.0717602056825,
          "e_diff": -2.4556356947869062e-11,
          "rmsd": 2.320566895307496e-08,
          "ediis": 4.8488109630373206e-11,
          "performance": {
            "total_time": 0.42607572
          }
        },
        "19": {
          "energy": -3006.0717602056857,
          "e_diff": -3.183231456205249e-12,
          "rmsd": 1.498873554591887e-08,
          "ediis": 1.178007460556842e-11,
          "performance": {
            "total_time": 0.430134149
          }
        },
        "20": {
          "energy": -3006.071760205685,
          "e_diff": 4.547473508864641e-13,
          "rmsd": 8.517230389410187e-09,
          "ediis": 3.0632142884905507e-12,
          "performance": {
            "total_time": 0.430267076
          }
        }
      },
      "NE_1e": -8698.587635137786,
      "kinetic_1e": 3005.6116500331423,
      "energy_1e": -5689.440942320625,
      "energy_2e": 1913.7976410189121,
      "energy_qed": 0.21447808254316225,
      "energy_qed_et": -37.78963866003191,
      "final_energy": -3006.071760205685,
      "n_iterations": 20,
      "performance": {
        "total_time": 11.610940244
      }
    },
    "CD": {
      "n_cholesky_vectors": 1235,
      "diagtol": 1e-05
    },
    "CCSD": {
      "iter": {
        "1": {
          "residual": 1.181119548318501,
          "correlation": 0.0,
          "performance": {
            "total_time": 29.644305737
          }
        },
        "2": {
          "residual": 0.17377017453772917,
          "correlation": -1.6503434281342684,
          "performance": {
            "total_time": 28.933227621
          }
        },
        "3": {
          "residual": 0.07247634171110454,
          "correlation": -1.6448439522681462,
          "performance": {
            "total_time": 28.611159478
          }
        },
        "4": {
          "residual": 0.02496315473726119,
          "correlation": -1.7179812255010143,
          "performance": {
            "total_time": 28.6712242
          }
        },
        "5": {
          "residual": 0.02198089972137953,
          "correlation": -1.7118074570064252,
          "performance": {
            "total_time": 28.784532491
          }
        },
        "6": {
          "residual": 0.01048457990417836,
          "correlation": -1.7244155872885163,
          "performance": {
            "total_time": 28.503600389
          }
        },
        "7": {
          "residual": 0.0081559207620075,
          "correlation": -1.7247537325738906,
          "performance": {
            "total_time": 28.38699559
          }
        },
        "8": {
          "residual": 0.0063087677418071685,
          "correlation": -1.7268533941200384,
          "performance": {
            "total_time": 28.42572546
          }
        },
        "9": {
          "residual": 0.006559225207237576,
          "correlation": -1.7274665204166766,
          "performance": {
            "total_time": 28.540128391
          }
        },
        "10": {
          "residual": 0.007728610769017368,
          "correlation": -1.7281376557034558,
          "performance": {
            "total_time": 28.836027525
          }
        },
        "11": {
          "residual": 0.0012793340011697943,
          "correlation": -1.7295961754462663,
          "performance": {
            "total_time": 28.428878384
          }
        },
        "12": {
          "residual": 0.0009109939275541912,
          "correlation": -1.7294675316890096,
          "performance": {
            "total_time": 28.49154944
          }
        },
        "13": {
          "residual": 0.0008592582428801579,
          "correlation": -1.7297423678429344,
          "performance": {
            "total_time": 28.456826425
          }
        },
        "14": {
          "residual": 0.0008816561508243488,
          "correlation": -1.7296990017466682,
          "performance": {
            "total_time": 28.519264522
          }
        },
        "15": {
          "residual": 0.0011523435006680653,
          "correlation": -1.7298162681506941,
          "performance": {
            "total_time": 28.418140403
          }
        },
        "16": {
          "residual": 0.0002564443417373694,
          "correlation": -1.7299046789566244,
          "performance": {
            "total_time": 28.664891805
          }
        },
        "17": {
          "residual": 0.00019283276779009015,
          "correlation": -1.7298918739728137,
          "performance": {
            "total_time": 28.438248213
          }
        },
        "18": {
          "residual": 0.00022344471858813856,
          "correlation": -1.7299313807121635,
          "performance": {
            "total_time": 28.538000699
          }
        },
        "19": {
          "residual": 0.0001966483077701434,
          "correlation": -1.72995045920937,
          "performance": {
            "total_time": 28.653135433
          }
        },
        "20": {
          "residual": 0.0002518382419052411,
          "correlation": -1.7299576949239857,
          "performance": {
            "total_time": 28.467157467
          }
        },
        "21": {
          "residual": 7.233925945688885e-05,
          "correlation": -1.7300059356618822,
          "performance": {
            "total_time": 29.338131273
          }
        },
        "22": {
          "residual": 5.959390732391909e-05,
          "correlation": -1.7299973901837744,
          "performance": {
            "total_time": 28.550504905
          }
        },
        "23": {
          "residual": 5.8765431756803186e-05,
          "correlation": -1.7299998256121427,
          "performance": {
            "total_time": 28.394882857
          }
        },
        "24": {
          "residual": 6.957533418009013e-05,
          "correlation": -1.7299973237000492,
          "performance": {
            "total_time": 28.479036233
          }
        },
        "25": {
          "residual": 8.88705459680741e-05,
          "correlation": -1.729999847736867,
          "performance": {
            "total_time": 28.483033725
          }
        },
        "26": {
          "residual": 2.1115823172601095e-05,
          "correlation": -1.7299966868180123,
          "performance": {
            "total_time": 28.458585456
          }
        },
        "27": {
          "residual": 1.4787932484145883e-05,
          "correlation": -1.7299988299335918,
          "performance": {
            "total_time": 28.369518231
          }
        },
        "28": {
          "residual": 1.479711830157274e-05,
          "correlation": -1.730000371723656,
          "performance": {
            "total_time": 28.483543739
          }
        },
        "29": {
          "residual": 1.4395002016854232e-05,
          "correlation": -1.7300019124146708,
          "performance": {
            "total_time": 28.544253951
          }
        },
        "30": {
          "residual": 1.7993504458990448e-05,
          "correlation": -1.730002135620201,
          "performance": {
            "total_time": 28.613085452
          }
        },
        "31": {
          "residual": 5.934282072437254e-06,
          "correlation": -1.7300051805638283,
          "performance": {
            "total_time": 28.592682476
          }
        },
        "32": {
          "residual": 4.860892672972273e-06,
          "correlation": -1.7300044274743123,
          "performance": {
            "total_time": 28.442888712
          }
        },
        "33": {
          "residual": 4.441258868902782e-06,
          "correlation": -1.7300044053335797,
          "performance": {
            "total_time": 28.505887253
          }
        },
        "34": {
          "residual": 4.912792875524187e-06,
          "correlation": -1.7300041913191884,
          "performance": {
            "total_time": 28.573775486
          }
        },
        "35": {
          "residual": 5.800505820472642e-06,
          "correlation": -1.7300043038443438,
          "performance": {
            "total_time": 28.505220735
          }
        },
        "36": {
          "residual": 2.1778882119915982e-06,
          "correlation": -1.7300039384513515,
          "performance": {
            "total_time": 28.437293705
          }
        },
        "37": {
          "residual": 1.7121369062398252e-06,
          "correlation": -1.7300041450857468,
          "performance": {
            "total_time": 28.672662164
          }
        },
        "38": {
          "residual": 1.6401296597054352e-06,
          "correlation": -1.7300043016984916,
          "performance": {
            "total_time": 28.442858251
          }
        },
        "39": {
          "residual": 1.5883010572920536e-06,
          "correlation": -1.7300044139446025,
          "performance": {
            "total_time": 28.607410941
          }
        },
        "40": {
          "residual": 1.8189062649557745e-06,
          "correlation": -1.7300044422036673,
          "performance": {
            "total_time": 28.851837305
          }
        },
        "41": {
          "residual": 9.718222281519703e-07,
          "correlation": -1.7300047829499479,
          "performance": {
            "total_time": 28.849536941
          }
        }
      },
      "n_iterations": 41,
      "final_energy": {
        "correlation": -1.7300047829499479,
        "total": -3007.801764988635
      },
      "performance": {
        "total_time": 1193.058668692
      }
    }
  },
  "molecule": {
    "name": "ortho_theta_86.08695652173913_phi_140.8695652173913",
    "basis": {
      "basisset": "6-311G*"
    },
    "nbf": 221,
    "nshells": 105,
    "nelectrons": 98,
    "nelectrons_alpha": 49,
    "nelectrons_beta": 49
  },
  "input": {
    "geometry": {
      "coordinates": [
        "C                  0.51932475    1.23303451   -0.03194925",
        "C                  1.94454413    1.26916358   -0.03672882",
        "C                  2.62037793    0.09283428   -0.02499003",
        "C                 -0.19603352    0.03013062    0.00102732",
        "H                 -0.02069420    2.17423764   -0.04336646",
        "H                  2.48281698    2.20891057   -0.03611879",
        "H                 -1.27770137    0.03990295    0.01166953",
        "N                  4.09213475    0.09594076    0.03662979",
        "O                  4.63930696   -1.02169275    0.14459220",
        "O                  4.66489883    1.19839699   -0.02327545",
        "C                  0.49428518   -1.16712649    0.02099746",
        "H                 -0.03251071   -2.11492669    0.05447935",
        "C                  1.96291176   -1.21653219   -0.02111314",
        "H                  2.44359113   -1.96306433    0.61513886",
        "Br                 2.17304025   -1.94912156   -1.90618750"
      ],
      "units": "angstrom"
    },
    "basis": {
      "basisset": "6-311G*"
    },
    "SCF": {
      "charge": 1,
      "multiplicity": 1,
      "conve": 1e-10,
      "convd": 1e-08,
      "scf_type": "restricted",
      "qed_omegas": [
        0.06614874648125418
      ],
      "qed_volumes": [],
      "qed_lambdas": [
        0.1
      ],
      "qed_polvecs": [
        [
          -0.7739029286442831,
          0.6296167326667604,
          0.068242413364671
        ]
      ]
    },
    "CC": {
      "threshold": 1e-06,
      "lshift": 0.0,
      "ccsd_maxiter": 200,
      "freeze": {
        "atomic": true
      }
    },
    "TASK": {
      "ccsd": true
    }
  }
}
