{
  "output": {
    "machine_info": {
      "date": "Tue Oct  7 03:42:46 2025",
      "nnodes": 8,
      "nproc_per_node": 4,
      "nproc_total": 32,
      "cpu": {
        "name": "AMD EPYC 7763 64-Core Processor                ",
        "cpu_memory_per_node_gib": 251,
        "total_cpu_memory_gib": 2008
      },
      "ngpus_per_node": 4,
      "ngpus_total": 32,
      "gpu": {
        "name": "NVIDIA A100-SXM4-40GB, CUDA v12.4",
        "memory_per_gpu_gib": 39,
        "gpu_memory_per_node_gib": 156,
        "total_gpu_memory_gib": 1248
      }
    },
    "system_info": {
      "nbf": 221,
      "nshells": 105,
      "nelectrons_total": 98,
      "nelectrons_alpha": 49,
      "nelectrons_beta": 49,
      "nbf_orig": 221
    },
    "SCF": {
      "nucl_rep_energy": 731.0227698813991,
      "xHF": 1.0,
      "iter": {
        "1": {
          "energy": -3011.19039921226,
          "e_diff": -3011.19039921226,
          "rmsd": 0.01641202328929507,
          "ediis": 1352.8066113584814,
          "performance": {
            "total_time": 0.180300777
          }
        },
        "2": {
          "energy": -3005.78119686362,
          "e_diff": 5.409202348640065,
          "rmsd": 0.006783371673753763,
          "ediis": 8.135057290738592,
          "performance": {
            "total_time": 0.350168351
          }
        },
        "3": {
          "energy": -3005.9424473575514,
          "e_diff": -0.16125049393122026,
          "rmsd": 0.002890385529627774,
          "ediis": 5.122275915228176,
          "performance": {
            "total_time": 0.342288886
          }
        },
        "4": {
          "energy": -3006.089493849911,
          "e_diff": -0.14704649235955003,
          "rmsd": 0.001117599911456591,
          "ediis": 0.12247684150424189,
          "performance": {
            "total_time": 0.349116852
          }
        },
        "5": {
          "energy": -3006.0955154203725,
          "e_diff": -0.006021570461598458,
          "rmsd": 0.0002710494837980302,
          "ediis": 0.016457556998048753,
          "performance": {
            "total_time": 0.353742369
          }
        },
        "6": {
          "energy": -3006.0962330008406,
          "e_diff": -0.0007175804680628062,
          "rmsd": 0.00012877119132004503,
          "ediis": 0.001001643424117805,
          "performance": {
            "total_time": 0.359112279
          }
        },
        "7": {
          "energy": -3006.0963219269815,
          "e_diff": -8.892614096112084e-05,
          "rmsd": 5.0619021601386035e-05,
          "ediis": 0.0001814031885430794,
          "performance": {
            "total_time": 0.364680994
          }
        },
        "8": {
          "energy": -3006.096338194295,
          "e_diff": -1.6267313640128123e-05,
          "rmsd": 2.122897056182858e-05,
          "ediis": 4.753394629937856e-05,
          "performance": {
            "total_time": 0.374286024
          }
        },
        "9": {
          "energy": -3006.096341948811,
          "e_diff": -3.7545160012086853e-06,
          "rmsd": 9.754246181190974e-06,
          "ediis": 9.708465899754642e-06,
          "performance": {
            "total_time": 0.380174298
          }
        },
        "10": {
          "energy": -3006.0963428834475,
          "e_diff": -9.346363185613882e-07,
          "rmsd": 4.815981187317665e-06,
          "ediis": 1.6675314450512984e-06,
          "performance": {
            "total_time": 0.400682784
          }
        },
        "11": {
          "energy": -3006.0963430936977,
          "e_diff": -2.1025016394560225e-07,
          "rmsd": 2.025394854734727e-06,
          "ediis": 1.9517893848293278e-07,
          "performance": {
            "total_time": 0.467500882
          }
        },
        "12": {
          "energy": -3006.0963431246723,
          "e_diff": -3.097466105828062e-08,
          "rmsd": 8.046075130919203e-07,
          "ediis": 3.012979716737595e-08,
          "performance": {
            "total_time": 0.417393959
          }
        },
        "13": {
          "energy": -3006.096343129941,
          "e_diff": -5.268702807370573e-09,
          "rmsd": 4.540698074576602e-07,
          "ediis": 7.898647743715702e-09,
          "performance": {
            "total_time": 0.420090015
          }
        },
        "14": {
          "energy": -3006.0963431317796,
          "e_diff": -1.8385435396339744e-09,
          "rmsd": 3.150528777781245e-07,
          "ediis": 2.4845947557634064e-09,
          "performance": {
            "total_time": 0.437716756
          }
        },
        "15": {
          "energy": -3006.096343132457,
          "e_diff": -6.775735528208315e-10,
          "rmsd": 1.4933548770597308e-07,
          "ediis": 6.223576589183235e-10,
          "performance": {
            "total_time": 0.410688401
          }
        },
        "16": {
          "energy": -3006.0963431326186,
          "e_diff": -1.6143530956469476e-10,
          "rmsd": 6.754453737443704e-08,
          "ediis": 1.252244695838657e-10,
          "performance": {
            "total_time": 0.503494426
          }
        },
        "17": {
          "energy": -3006.09634313265,
          "e_diff": -3.1377567211166024e-11,
          "rmsd": 3.398973574571436e-08,
          "ediis": 2.5755645249231913e-11,
          "performance": {
            "total_time": 0.438738146
          }
        },
        "18": {
          "energy": -3006.096343132655,
          "e_diff": -5.002220859751105e-12,
          "rmsd": 9.60230130332361e-09,
          "ediis": 3.561485289742363e-12,
          "performance": {
            "total_time": 0.484561365
          }
        }
      },
      "NE_1e": -8614.602063007424,
      "kinetic_1e": 3005.591735675076,
      "energy_1e": -5608.130885652487,
      "energy_2e": 1871.7081909722303,
      "energy_qed": 0.1830233460631554,
      "energy_qed_et": -37.37119113014054,
      "final_energy": -3006.096343132655,
      "n_iterations": 18,
      "performance": {
        "total_time": 15.49828812
      }
    },
    "CD": {
      "n_cholesky_vectors": 1241,
      "diagtol": 1e-05
    },
    "CCSD": {
      "iter": {
        "1": {
          "residual": 1.182147606659061,
          "correlation": 0.0,
          "performance": {
            "total_time": 29.322358721
          }
        },
        "2": {
          "residual": 0.17076548627483717,
          "correlation": -1.713370098682369,
          "performance": {
            "total_time": 28.483289566
          }
        },
        "3": {
          "residual": 0.07213096427916728,
          "correlation": -1.6623207667243733,
          "performance": {
            "total_time": 28.597252199
          }
        },
        "4": {
          "residual": 0.02285952392279098,
          "correlation": -1.7388795152802357,
          "performance": {
            "total_time": 28.497397356
          }
        },
        "5": {
          "residual": 0.019311841508306577,
          "correlation": -1.7291150568661036,
          "performance": {
            "total_time": 28.439278281
          }
        },
        "6": {
          "residual": 0.008590837417879579,
          "correlation": -1.740519185068254,
          "performance": {
            "total_time": 28.274002423
          }
        },
        "7": {
          "residual": 0.0058925623667881065,
          "correlation": -1.7402692374891195,
          "performance": {
            "total_time": 28.248367818
          }
        },
        "8": {
          "residual": 0.003948929791645353,
          "correlation": -1.7417739413993552,
          "performance": {
            "total_time": 28.319381182
          }
        },
        "9": {
          "residual": 0.0031015910257824494,
          "correlation": -1.74193006426887,
          "performance": {
            "total_time": 28.231068838
          }
        },
        "10": {
          "residual": 0.002871423191860487,
          "correlation": -1.7423483837084062,
          "performance": {
            "total_time": 28.20330085
          }
        },
        "11": {
          "residual": 0.0006434801062029451,
          "correlation": -1.7429229747227,
          "performance": {
            "total_time": 28.244345719
          }
        },
        "12": {
          "residual": 0.0005038779206648342,
          "correlation": -1.7429483361989302,
          "performance": {
            "total_time": 28.246226414
          }
        },
        "13": {
          "residual": 0.0004135978162012214,
          "correlation": -1.7429930965068057,
          "performance": {
            "total_time": 28.132731935
          }
        },
        "14": {
          "residual": 0.0004484466991897443,
          "correlation": -1.7429688417994618,
          "performance": {
            "total_time": 28.226281446
          }
        },
        "15": {
          "residual": 0.0004579059216800605,
          "correlation": -1.7429860557244239,
          "performance": {
            "total_time": 28.178323844
          }
        },
        "16": {
          "residual": 0.0001007012767109212,
          "correlation": -1.7429731655452807,
          "performance": {
            "total_time": 28.226014483
          }
        },
        "17": {
          "residual": 6.845780432551839e-05,
          "correlation": -1.7429819464696572,
          "performance": {
            "total_time": 28.292582727
          }
        },
        "18": {
          "residual": 6.20434749015507e-05,
          "correlation": -1.742991198797261,
          "performance": {
            "total_time": 28.244308936
          }
        },
        "19": {
          "residual": 4.7857319631532246e-05,
          "correlation": -1.7429928288970575,
          "performance": {
            "total_time": 28.161630014
          }
        },
        "20": {
          "residual": 4.9851359257407115e-05,
          "correlation": -1.7429944156938015,
          "performance": {
            "total_time": 28.12138672
          }
        },
        "21": {
          "residual": 1.725996338699594e-05,
          "correlation": -1.7429998237339497,
          "performance": {
            "total_time": 28.375597082
          }
        },
        "22": {
          "residual": 1.4416395602856735e-05,
          "correlation": -1.7429996179892624,
          "performance": {
            "total_time": 28.135522471
          }
        },
        "23": {
          "residual": 9.544910142496749e-06,
          "correlation": -1.7429990052765878,
          "performance": {
            "total_time": 28.244906488
          }
        },
        "24": {
          "residual": 1.0868581503145388e-05,
          "correlation": -1.742997983992165,
          "performance": {
            "total_time": 27.988890627
          }
        },
        "25": {
          "residual": 8.493177144355338e-06,
          "correlation": -1.7429980815680295,
          "performance": {
            "total_time": 28.082448889
          }
        },
        "26": {
          "residual": 3.600492885930516e-06,
          "correlation": -1.7429963077700263,
          "performance": {
            "total_time": 28.046216643
          }
        },
        "27": {
          "residual": 2.5829682372740282e-06,
          "correlation": -1.7429973165120054,
          "performance": {
            "total_time": 27.999596822
          }
        },
        "28": {
          "residual": 2.5019181945281672e-06,
          "correlation": -1.7429974879304069,
          "performance": {
            "total_time": 28.066591593
          }
        },
        "29": {
          "residual": 2.3721394540685668e-06,
          "correlation": -1.7429976198107155,
          "performance": {
            "total_time": 28.122891809
          }
        },
        "30": {
          "residual": 2.6569258898466142e-06,
          "correlation": -1.742997663563516,
          "performance": {
            "total_time": 28.04569283
          }
        },
        "31": {
          "residual": 6.483825365957338e-07,
          "correlation": -1.7429977901646376,
          "performance": {
            "total_time": 28.171082625
          }
        }
      },
      "n_iterations": 31,
      "final_energy": {
        "correlation": -1.7429977901646376,
        "total": -3007.8393409228197
      },
      "performance": {
        "total_time": 891.219548493
      }
    }
  },
  "molecule": {
    "name": "para_theta_156.52173913043478_phi_31.304347826086957",
    "basis": {
      "basisset": "6-311G*"
    },
    "nbf": 221,
    "nshells": 105,
    "nelectrons": 98,
    "nelectrons_alpha": 49,
    "nelectrons_beta": 49
  },
  "input": {
    "geometry": {
      "coordinates": [
        "C                 -0.80658313    1.22973465    0.03041801",
        "C                  0.56153576    1.23725234    0.01622618",
        "C                  1.22915389    0.01001055    0.01220575",
        "H                 -1.36676923    2.15803094    0.04420367",
        "H                  1.14116413    2.14927050    0.01037697",
        "N                  2.71357475    0.03144573   -0.00289824",
        "O                  3.28013247   -1.09741954   -0.00254733",
        "O                  3.24714953    1.17621948   -0.01252002",
        "C                 -0.77042978   -1.26805414    0.04039660",
        "H                 -1.30353926   -2.21202933    0.06122375",
        "C                  0.59726287   -1.23605918    0.02634378",
        "H                  1.20308359   -2.13089607    0.02793117",
        "C                 -1.56287141   -0.03049318    0.01040538",
        "H                 -2.41148563   -0.03994459    0.70143946",
        "Br                -2.40993182   -0.04931830   -1.82359612"
      ],
      "units": "angstrom"
    },
    "basis": {
      "basisset": "6-311G*"
    },
    "SCF": {
      "charge": 1,
      "multiplicity": 1,
      "conve": 1e-10,
      "convd": 1e-08,
      "scf_type": "restricted",
      "qed_omegas": [
        0.06614874648125418
      ],
      "qed_volumes": [],
      "qed_lambdas": [
        0.1
      ],
      "qed_polvecs": [
        [
          0.34040162195709767,
          0.20700281196073178,
          -0.917211301505453
        ]
      ]
    },
    "CC": {
      "threshold": 1e-06,
      "lshift": 0.0,
      "ccsd_maxiter": 200,
      "freeze": {
        "atomic": true
      }
    },
    "TASK": {
      "ccsd": true
    }
  }
}
